LICENSE
MANIFEST.in
README.md
setup.py
zhiqiang/__init__.py
zhiqiang.egg-info/PKG-INFO
zhiqiang.egg-info/SOURCES.txt
zhiqiang.egg-info/dependency_links.txt
zhiqiang.egg-info/top_level.txt
zhiqiang/agents/__init__.py
zhiqiang/agents/acq_entropy.py
zhiqiang/agents/acv_entropy.py
zhiqiang/agents/dqn_double.py
zhiqiang/agents/dqn_mstep.py
zhiqiang/agents/dqn_priority.py
zhiqiang/agents/dqn_vanila.py
zhiqiang/agents/policy_mstep.py
zhiqiang/envs/__init__.py
zhiqiang/replay_buffers/__init__.py
zhiqiang/replay_buffers/priority_buffer.py
zhiqiang/replay_buffers/simple_buffer.py
zhiqiang/trainers/__init__.py
zhiqiang/trainers/paral_trainer.py
zhiqiang/trainers/paral_trainer_rebuild.py
zhiqiang/trainers/simple_trainer.py
zhiqiang/utils/__init__.py
zhiqiang/utils/basic_settings.py
zhiqiang/utils/data_parallelism.py
zhiqiang/utils/data_parallelism_rebuild.py
zhiqiang/utils/log_parser.py
zhiqiang/utils/torch_utils.py
zhiqiang/utils/uct_simple.py